digirock/__init__.py
digirock/_base.py
digirock/_exceptions.py
digirock/_mineral_lib.py
digirock/_rock.py
digirock/_stress.py
digirock/_version.py
digirock/datasets.py
digirock/elastic.py
digirock/typing.py
digirock/_fluids/__init__.py
digirock/_fluids/_fluid.py
digirock/_fluids/_fluid_loaders.py
digirock/_fluids/_fluid_mod.py
digirock/_fluids/_gas.py
digirock/_fluids/_oil.py
digirock/_fluids/_water.py
digirock/_frames/__init__.py
digirock/_frames/_adjust.py
digirock/_frames/_frames.py
digirock/_frames/_minerals.py
digirock/_frames/_poro_adjust.py
digirock/fluids/__init__.py
digirock/fluids/bw92.py
digirock/fluids/ecl.py
digirock/models/__init__.py
digirock/models/_cemented_sand.py
digirock/models/_hsw.py
digirock/models/_kuster_toksoz.py
digirock/models/_mod.py
digirock/utils/__init__.py
digirock/utils/_decorators.py
digirock/utils/_utils.py
digirock/utils/ecl.py
digirock/utils/file.py
digirock-0.1.2.dist-info/LICENSE
digirock-0.1.2.dist-info/METADATA
digirock-0.1.2.dist-info/WHEEL
digirock-0.1.2.dist-info/top_level.txt
digirock-0.1.2.dist-info/RECORD
