Metadata-Version: 2.1
Name: digirock
Version: 0.1.2
Summary: Flexible tool to create custom digital rock models.
Home-page: https://github.com/trhallam/digirock/
Author-email: trhallam@gmail.com
License: MIT
Platform: UNKNOWN
Requires-Python: >=3.8
License-File: LICENSE
Requires-Dist: xarray
Requires-Dist: numpy
Requires-Dist: scipy
Requires-Dist: numba
Requires-Dist: addict
Requires-Dist: more-itertools
Requires-Dist: rich
Requires-Dist: pooch
Provides-Extra: docs
Requires-Dist: mkdocs ; extra == 'docs'
Requires-Dist: mkdocstrings ; extra == 'docs'
Requires-Dist: mkdocs-material ; extra == 'docs'
Requires-Dist: mkdocs-material-extensions ; extra == 'docs'
Requires-Dist: mkdocs-simple-plugin ; extra == 'docs'
Requires-Dist: mkdocs-jupyter ; extra == 'docs'
Requires-Dist: mkautodoc ; extra == 'docs'
Requires-Dist: jupyterlab ; extra == 'docs'
Requires-Dist: matplotlib ; extra == 'docs'
Provides-Extra: test
Requires-Dist: pytest ; extra == 'test'
Requires-Dist: pytest-cov ; extra == 'test'
Requires-Dist: pandas ; extra == 'test'
Requires-Dist: numpy ; extra == 'test'
Requires-Dist: xarray ; extra == 'test'
Requires-Dist: hypothesis ; extra == 'test'
